{
    "overall_execution": {
        "start": "2025-04-16 12:01:10+00:00",
        "end": "2025-04-16 12:03:56+00:00"
    },
    "datafold_1_execution": {
        "start": "2025-04-16 12:01:11+00:00",
        "end": "2025-04-16 12:01:42+00:00"
    },
    "datafold_2_execution": {
        "start": "2025-04-16 12:01:42+00:00",
        "end": "2025-04-16 12:02:14+00:00"
    },
    "datafold_3_execution": {
        "start": "2025-04-16 12:02:14+00:00",
        "end": "2025-04-16 12:02:48+00:00"
    },
    "datafold_4_execution": {
        "start": "2025-04-16 12:02:48+00:00",
        "end": "2025-04-16 12:03:21+00:00"
    },
    "datafold_5_execution": {
        "start": "2025-04-16 12:03:21+00:00",
        "end": "2025-04-16 12:03:54+00:00"
    }
}